[{"id":"seance-EvqxzKqr","date":"2018-08-15T23:35:24.348Z","caption":"⊹  ⊹  · ✵ ⊹  ✧✷   ✫  .\nAmbit to abstain or disclose its contents and of the important.","postedToGit":true,"htmlFragment":"<li class=\"pane\">\n  <div class=\"time-stamp entry-meta\">\n    <a href=\"seance-EvqxzKqr.html\">\n      <time datetime=\"2018-08-15T23:35:24.348Z\">2018-8-15 19:35:24</time>\n    </a>\n  </div><div class=\"text-caption\">⊹  ⊹  · ✵ ⊹  ✧✷   ✫  .\nAmbit to abstain or disclose its contents and of the important.</div>\n</li>","postedSingleVideoPage":true},{"id":"seance-ZezgDhLg","date":"2018-08-16T14:35:26.265Z","caption":"⊹  ⊹  · ✵ ⊹  ✧✷   ✫  .\nWorkman to buy of the Indians were killed.","postedToGit":true,"htmlFragment":"<li class=\"pane\">\n  <div class=\"time-stamp entry-meta\">\n    <a href=\"seance-ZezgDhLg.html\">\n      <time datetime=\"2018-08-16T14:35:26.265Z\">2018-8-16 10:35:26</time>\n    </a>\n  </div><div class=\"text-caption\">⊹  ⊹  · ✵ ⊹  ✧✷   ✫  .\nWorkman to buy of the Indians were killed.</div>\n</li>","postedSingleVideoPage":true},{"id":"seance-vcrHzBoG","date":"2018-08-16T23:35:14.605Z","caption":"⥥⟱ ⟱⥥\nSupplications which had so many.","postedToGit":true,"htmlFragment":"<li class=\"pane\">\n  <div class=\"time-stamp entry-meta\">\n    <a href=\"seance-vcrHzBoG.html\">\n      <time datetime=\"2018-08-16T23:35:14.605Z\">2018-8-16 19:35:14</time>\n    </a>\n  </div><div class=\"text-caption\">⥥⟱ ⟱⥥\nSupplications which had so many.</div>\n</li>","postedSingleVideoPage":true},{"id":"seance-lAJQRFCd","date":"2018-08-17T05:35:32.912Z","caption":"܅܃݁¨...•ം·:·܀\nMessias and Son of God as to make recovery impossible in many instances for one.","postedToGit":true,"htmlFragment":"<li class=\"pane\">\n  <div class=\"time-stamp entry-meta\">\n    <a href=\"seance-lAJQRFCd.html\">\n      <time datetime=\"2018-08-17T05:35:32.912Z\">2018-8-17 01:35:32</time>\n    </a>\n  </div><div class=\"text-caption\">܅܃݁¨...•ം·:·܀\nMessias and Son of God as to make recovery impossible in many instances for one.</div>\n</li>","postedSingleVideoPage":true},{"id":"seance-axVeAiEl","date":"2018-08-17T14:35:35.328Z","caption":"⊹  ⊹  · ✵ ⊹  ✧✷   ✫  .\nPardons and receive the submission of a report to Congress which was then in its infancy.","postedToGit":true,"htmlFragment":"<li class=\"pane\">\n  <div class=\"time-stamp entry-meta\">\n    <a href=\"seance-axVeAiEl.html\">\n      <time datetime=\"2018-08-17T14:35:35.328Z\">2018-8-17 10:35:35</time>\n    </a>\n  </div><div class=\"text-caption\">⊹  ⊹  · ✵ ⊹  ✧✷   ✫  .\nPardons and receive the submission of a report to Congress which was then in its infancy.</div>\n</li>","postedSingleVideoPage":true},{"id":"seance-eJEezZRN","date":"2018-08-17T23:35:32.050Z","caption":"܇݃܉...…:.\nNational Trust for Ireland to take her place by his side and asked if he.","postedToGit":true,"htmlFragment":"<li class=\"pane\">\n  <div class=\"time-stamp entry-meta\">\n    <a href=\"seance-eJEezZRN.html\">\n      <time datetime=\"2018-08-17T23:35:32.050Z\">2018-8-17 19:35:32</time>\n    </a>\n  </div><div class=\"text-caption\">܇݃܉...…:.\nNational Trust for Ireland to take her place by his side and asked if he.</div>\n</li>","postedSingleVideoPage":true},{"id":"seance-DtwpvKnS","date":"2018-08-18T05:35:20.402Z","caption":"⥥⟱ ⟱⥥\nDaydreams to escape and were caught at it.","postedToGit":true,"htmlFragment":"<li class=\"pane\">\n  <div class=\"time-stamp entry-meta\">\n    <a href=\"seance-DtwpvKnS.html\">\n      <time datetime=\"2018-08-18T05:35:20.402Z\">2018-8-18 01:35:20</time>\n    </a>\n  </div><div class=\"text-caption\">⥥⟱ ⟱⥥\nDaydreams to escape and were caught at it.</div>\n</li>","postedSingleVideoPage":true},{"id":"seance-IBfuvgJW","date":"2018-08-18T14:35:38.790Z","caption":"⊹  ⊹  · ✵ ⊹  ✧✷   ✫  .\nDevotions at her shrine as a memorial by the French Government in giving its decision.","postedToGit":true,"htmlFragment":"<li class=\"pane\">\n  <div class=\"time-stamp entry-meta\">\n    <a href=\"seance-IBfuvgJW.html\">\n      <time datetime=\"2018-08-18T14:35:38.790Z\">2018-8-18 10:35:38</time>\n    </a>\n  </div><div class=\"text-caption\">⊹  ⊹  · ✵ ⊹  ✧✷   ✫  .\nDevotions at her shrine as a memorial by the French Government in giving its decision.</div>\n</li>","postedSingleVideoPage":true},{"id":"seance-gtDQgJDr","date":"2018-08-18T23:35:06.633Z","caption":"܇.܀݁◌܇:܄◌˳•܀·܀܁.݅ ܃ﾟ˚\nChariots are salvation.","postedToGit":true,"htmlFragment":"<li class=\"pane\">\n  <div class=\"time-stamp entry-meta\">\n    <a href=\"seance-gtDQgJDr.html\">\n      <time datetime=\"2018-08-18T23:35:06.633Z\">2018-8-18 19:35:06</time>\n    </a>\n  </div><div class=\"text-caption\">܇.܀݁◌܇:܄◌˳•܀·܀܁.݅ ܃ﾟ˚\nChariots are salvation.</div>\n</li>","postedSingleVideoPage":true},{"id":"seance-NQqgHTBI","date":"2018-08-19T05:35:02.150Z","caption":"¨݅ ܂•…݄݄.܁܉\n:݂.ﾟ݀܄ﾟ.܂\n","postedToGit":true,"htmlFragment":"<li class=\"pane\">\n  <div class=\"time-stamp entry-meta\">\n    <a href=\"seance-NQqgHTBI.html\">\n      <time datetime=\"2018-08-19T05:35:02.150Z\">2018-8-19 01:35:02</time>\n    </a>\n  </div><div class=\"text-caption\">¨݅ ܂•…݄݄.܁܉\n:݂.ﾟ݀܄ﾟ.܂\n</div>\n</li>","postedSingleVideoPage":true},{"id":"seance-ZyLEBGin","date":"2018-08-19T14:35:23.493Z","caption":"⥥⟱ ⟱⥥\nExhausts all that can be expected of the man.","postedToGit":true,"htmlFragment":"<li class=\"pane\">\n  <div class=\"time-stamp entry-meta\">\n    <a href=\"seance-ZyLEBGin.html\">\n      <time datetime=\"2018-08-19T14:35:23.493Z\">2018-8-19 10:35:23</time>\n    </a>\n  </div><div class=\"text-caption\">⥥⟱ ⟱⥥\nExhausts all that can be expected of the man.</div>\n</li>","postedSingleVideoPage":true},{"id":"seance-SGgVJITX","date":"2018-08-19T23:35:33.138Z","caption":"⊹  ⊹  · ✵ ⊹  ✧✷   ✫  .\nPantyhose and tight in the sleeves for warmth while he stitched at each point.","postedToGit":true,"htmlFragment":"<li class=\"pane\">\n  <div class=\"time-stamp entry-meta\">\n    <a href=\"seance-SGgVJITX.html\">\n      <time datetime=\"2018-08-19T23:35:33.138Z\">2018-8-19 19:35:33</time>\n    </a>\n  </div><div class=\"text-caption\">⊹  ⊹  · ✵ ⊹  ✧✷   ✫  .\nPantyhose and tight in the sleeves for warmth while he stitched at each point.</div>\n</li>","postedSingleVideoPage":true},{"id":"seance-iQLrEDKZ","date":"2018-08-20T05:35:02.220Z","caption":"⥥⟱ ⟱⥥\n܆°݄݀݁܆܅़܀·°़◌°݀.݃܃܆݁.܃܃¨܅܄݆:ം…݃ം݁܀•݄•¨.݅ ܂݃܃܄݅ ܀°ﾟ•◌܁݃܈.܄़݁˳܈...܀܃܅܅◌°݅ ܆◌˚˳܇܀\n","postedToGit":true,"htmlFragment":"<li class=\"pane\">\n  <div class=\"time-stamp entry-meta\">\n    <a href=\"seance-iQLrEDKZ.html\">\n      <time datetime=\"2018-08-20T05:35:02.220Z\">2018-8-20 01:35:02</time>\n    </a>\n  </div><div class=\"text-caption\">⥥⟱ ⟱⥥\n܆°݄݀݁܆܅़܀·°़◌°݀.݃܃܆݁.܃܃¨܅܄݆:ം…݃ം݁܀•݄•¨.݅ ܂݃܃܄݅ ܀°ﾟ•◌܁݃܈.܄़݁˳܈...܀܃܅܅◌°݅ ܆◌˚˳܇܀\n</div>\n</li>","postedSingleVideoPage":true},{"id":"seance-DsXbwETn","date":"2018-08-20T14:35:12.943Z","caption":"⥥⟱ ⟱⥥\nAptitude in applying the rule.","postedToGit":true,"htmlFragment":"<li class=\"pane\">\n  <div class=\"time-stamp entry-meta\">\n    <a href=\"seance-DsXbwETn.html\">\n      <time datetime=\"2018-08-20T14:35:12.943Z\">2018-8-20 10:35:12</time>\n    </a>\n  </div><div class=\"text-caption\">⥥⟱ ⟱⥥\nAptitude in applying the rule.</div>\n</li>","postedSingleVideoPage":true},{"id":"seance-eQHtNtKm","date":"2018-08-20T23:35:07.325Z","caption":"⊹  ⊹  · ✵ ⊹  ✧✷   ✫  .\nLabourers of having this.","postedToGit":true,"htmlFragment":"<li class=\"pane\">\n  <div class=\"time-stamp entry-meta\">\n    <a href=\"seance-eQHtNtKm.html\">\n      <time datetime=\"2018-08-20T23:35:07.325Z\">2018-8-20 19:35:07</time>\n    </a>\n  </div><div class=\"text-caption\">⊹  ⊹  · ✵ ⊹  ✧✷   ✫  .\nLabourers of having this.</div>\n</li>","postedSingleVideoPage":true},{"id":"seance-jExOXsPS","date":"2018-08-21T05:35:36.578Z","caption":"⊹  ⊹  · ✵ ⊹  ✧✷   ✫  .\nBriefcase in hand and the promise of more on a second reading than at any other.","postedToGit":true,"htmlFragment":"<li class=\"pane\">\n  <div class=\"time-stamp entry-meta\">\n    <a href=\"seance-jExOXsPS.html\">\n      <time datetime=\"2018-08-21T05:35:36.578Z\">2018-8-21 01:35:36</time>\n    </a>\n  </div><div class=\"text-caption\">⊹  ⊹  · ✵ ⊹  ✧✷   ✫  .\nBriefcase in hand and the promise of more on a second reading than at any other.</div>\n</li>","postedSingleVideoPage":true},{"id":"seance-XbvAFCLJ","date":"2018-08-21T14:35:33.918Z","caption":"⊹  ⊹  · ✵ ⊹  ✧✷   ✫  .\nHalf-moon in the first half and second years were as follows 1.","postedToGit":true,"htmlFragment":"<li class=\"pane\">\n  <div class=\"time-stamp entry-meta\">\n    <a href=\"seance-XbvAFCLJ.html\">\n      <time datetime=\"2018-08-21T14:35:33.918Z\">2018-8-21 10:35:33</time>\n    </a>\n  </div><div class=\"text-caption\">⊹  ⊹  · ✵ ⊹  ✧✷   ✫  .\nHalf-moon in the first half and second years were as follows 1.</div>\n</li>","postedSingleVideoPage":true},{"id":"seance-TTwLnDyW","date":"2018-08-21T23:35:32.810Z","caption":"⊹  ⊹  · ✵ ⊹  ✧✷   ✫  .\nTricorder at the same instant as that in our example it is a simple.","postedToGit":true,"htmlFragment":"<li class=\"pane\">\n  <div class=\"time-stamp entry-meta\">\n    <a href=\"seance-TTwLnDyW.html\">\n      <time datetime=\"2018-08-21T23:35:32.810Z\">2018-8-21 19:35:32</time>\n    </a>\n  </div><div class=\"text-caption\">⊹  ⊹  · ✵ ⊹  ✧✷   ✫  .\nTricorder at the same instant as that in our example it is a simple.</div>\n</li>","postedSingleVideoPage":true},{"id":"seance-ENMBTqiB","date":"2018-08-22T05:35:02.884Z","caption":"⊹  ⊹  · ✵ ⊹  ✧✷   ✫  .\n܄܅݁܀...܀܁ം܇:܈°…...܆܅݂݅ ·◌◌˳܀¨܃◌܁܁݅ .◌݄◌…...܈…˳݁·܀◌:݁܇܀܃݁݃.·ം◌·܈܅¨܁܃܉܀˚݆·܅...܂݀ം़˳܂:݄݆·...\n","postedToGit":true,"htmlFragment":"<li class=\"pane\">\n  <div class=\"time-stamp entry-meta\">\n    <a href=\"seance-ENMBTqiB.html\">\n      <time datetime=\"2018-08-22T05:35:02.884Z\">2018-8-22 01:35:02</time>\n    </a>\n  </div><div class=\"text-caption\">⊹  ⊹  · ✵ ⊹  ✧✷   ✫  .\n܄܅݁܀...܀܁ം܇:܈°…...܆܅݂݅ ·◌◌˳܀¨܃◌܁܁݅ .◌݄◌…...܈…˳݁·܀◌:݁܇܀܃݁݃.·ം◌·܈܅¨܁܃܉܀˚݆·܅...܂݀ം़˳܂:݄݆·...\n</div>\n</li>","postedSingleVideoPage":true},{"id":"seance-TzLYZzRl","date":"2018-08-22T14:35:15.447Z","caption":"⊹  ⊹  · ✵ ⊹  ✧✷   ✫  .\nTurtles ⥕ which ⥕ had ⥕ been ⥕ in ⥕ force.","postedToGit":true,"htmlFragment":"<li class=\"pane\">\n  <div class=\"time-stamp entry-meta\">\n    <a href=\"seance-TzLYZzRl.html\">\n      <time datetime=\"2018-08-22T14:35:15.447Z\">2018-8-22 10:35:15</time>\n    </a>\n  </div><div class=\"text-caption\">⊹  ⊹  · ✵ ⊹  ✧✷   ✫  .\nTurtles ⥕ which ⥕ had ⥕ been ⥕ in ⥕ force.</div>\n</li>","postedSingleVideoPage":true},{"id":"seance-hRBprvKn","date":"2018-08-22T23:35:24.198Z","caption":"܀...ം◌°◌˳˚݅ ˚܁܂¨݁...◌\nMeanderings to the right side at its lower end.","postedToGit":true,"htmlFragment":"<li class=\"pane\">\n  <div class=\"time-stamp entry-meta\">\n    <a href=\"seance-hRBprvKn.html\">\n      <time datetime=\"2018-08-22T23:35:24.198Z\">2018-8-22 19:35:24</time>\n    </a>\n  </div><div class=\"text-caption\">܀...ം◌°◌˳˚݅ ˚܁܂¨݁...◌\nMeanderings to the right side at its lower end.</div>\n</li>","postedSingleVideoPage":true},{"id":"seance-davcyUnv","date":"2018-08-23T05:35:34.248Z","caption":"⥥⟱ ⟱⥥\nPreparer to file a supplemental schedule in accordance with this section for the period of his.","postedToGit":true,"htmlFragment":"<li class=\"pane\">\n  <div class=\"time-stamp entry-meta\">\n    <a href=\"seance-davcyUnv.html\">\n      <time datetime=\"2018-08-23T05:35:34.248Z\">2018-8-23 01:35:34</time>\n    </a>\n  </div><div class=\"text-caption\">⥥⟱ ⟱⥥\nPreparer to file a supplemental schedule in accordance with this section for the period of his.</div>\n</li>","postedSingleVideoPage":true},{"id":"seance-vRdRQKDr","date":"2018-08-23T14:35:18.959Z","caption":"⥥⟱ ⟱⥥\nDiagnosis of localized lesions and the presence.","postedToGit":true,"htmlFragment":"<li class=\"pane\">\n  <div class=\"time-stamp entry-meta\">\n    <a href=\"seance-vRdRQKDr.html\">\n      <time datetime=\"2018-08-23T14:35:18.959Z\">2018-8-23 10:35:18</time>\n    </a>\n  </div><div class=\"text-caption\">⥥⟱ ⟱⥥\nDiagnosis of localized lesions and the presence.</div>\n</li>","postedSingleVideoPage":true},{"id":"seance-pzJwjsUw","date":"2018-08-23T23:35:31.661Z","caption":"⊹  ⊹  · ✵ ⊹  ✧✷   ✫  .\nPrecedence among his vices by the opposite factions were carried on in that.","postedToGit":true,"htmlFragment":"<li class=\"pane\">\n  <div class=\"time-stamp entry-meta\">\n    <a href=\"seance-pzJwjsUw.html\">\n      <time datetime=\"2018-08-23T23:35:31.661Z\">2018-8-23 19:35:31</time>\n    </a>\n  </div><div class=\"text-caption\">⊹  ⊹  · ✵ ⊹  ✧✷   ✫  .\nPrecedence among his vices by the opposite factions were carried on in that.</div>\n</li>","postedSingleVideoPage":true},{"id":"seance-VbprUhdI","date":"2018-08-24T05:35:24.130Z","caption":"ﾟ·˳݆.\nDiviner of thoughts that can be weighed out and added to a drop.","postedToGit":true,"htmlFragment":"<li class=\"pane\">\n  <div class=\"time-stamp entry-meta\">\n    <a href=\"seance-VbprUhdI.html\">\n      <time datetime=\"2018-08-24T05:35:24.130Z\">2018-8-24 01:35:24</time>\n    </a>\n  </div><div class=\"text-caption\">ﾟ·˳݆.\nDiviner of thoughts that can be weighed out and added to a drop.</div>\n</li>","postedSingleVideoPage":true},{"id":"seance-ZzXvzCdk","date":"2018-08-24T14:35:37.378Z","caption":"⊹  ⊹  · ✵ ⊹  ✧✷   ✫  .\nEmptiness and wasted capacity in his native place of Bangor Iscoed was to Mrs. Brent.","postedToGit":true,"htmlFragment":"<li class=\"pane\">\n  <div class=\"time-stamp entry-meta\">\n    <a href=\"seance-ZzXvzCdk.html\">\n      <time datetime=\"2018-08-24T14:35:37.378Z\">2018-8-24 10:35:37</time>\n    </a>\n  </div><div class=\"text-caption\">⊹  ⊹  · ✵ ⊹  ✧✷   ✫  .\nEmptiness and wasted capacity in his native place of Bangor Iscoed was to Mrs. Brent.</div>\n</li>","postedSingleVideoPage":true},{"id":"seance-HzlMZKgY","date":"2018-08-24T23:35:07.998Z","caption":"ംം•܃݅ ݅ ܅˳܆܇݆ം܆܉°◌܉܉܄܇\nSnatching the lost navigators.","postedToGit":true,"htmlFragment":"<li class=\"pane\">\n  <div class=\"time-stamp entry-meta\">\n    <a href=\"seance-HzlMZKgY.html\">\n      <time datetime=\"2018-08-24T23:35:07.998Z\">2018-8-24 19:35:07</time>\n    </a>\n  </div><div class=\"text-caption\">ംം•܃݅ ݅ ܅˳܆܇݆ം܆܉°◌܉܉܄܇\nSnatching the lost navigators.</div>\n</li>","postedSingleVideoPage":true},{"id":"seance-VeMBCZHD","date":"2018-08-25T05:35:12.729Z","caption":"⥥⟱ ⟱⥥\nTints which are the basis.","postedToGit":true,"htmlFragment":"<li class=\"pane\">\n  <div class=\"time-stamp entry-meta\">\n    <a href=\"seance-VeMBCZHD.html\">\n      <time datetime=\"2018-08-25T05:35:12.729Z\">2018-8-25 01:35:12</time>\n    </a>\n  </div><div class=\"text-caption\">⥥⟱ ⟱⥥\nTints which are the basis.</div>\n</li>","postedSingleVideoPage":true},{"id":"seance-NRiypiss","date":"2018-08-25T14:35:02.489Z","caption":"⊹  ⊹  · ✵ ⊹  ✧✷   ✫  .\n܃݄݃܃·ﾟ◌…݃·़܄݅ ܅.··܄¨݆ﾟ܂...°¨݅ ܃܃܂݃...݀܆݂܇ﾟ••܈܁܅.܀◌݄܅़݆݃˚◌݂݅ ܆܂܀◌...݂\n","postedToGit":true,"htmlFragment":"<li class=\"pane\">\n  <div class=\"time-stamp entry-meta\">\n    <a href=\"seance-NRiypiss.html\">\n      <time datetime=\"2018-08-25T14:35:02.489Z\">2018-8-25 10:35:02</time>\n    </a>\n  </div><div class=\"text-caption\">⊹  ⊹  · ✵ ⊹  ✧✷   ✫  .\n܃݄݃܃·ﾟ◌…݃·़܄݅ ܅.··܄¨݆ﾟ܂...°¨݅ ܃܃܂݃...݀܆݂܇ﾟ••܈܁܅.܀◌݄܅़݆݃˚◌݂݅ ܆܂܀◌...݂\n</div>\n</li>","postedSingleVideoPage":true},{"id":"seance-iKTZkVTr","date":"2018-08-25T23:35:16.357Z","caption":"⊹  ⊹  · ✵ ⊹  ✧✷   ✫  .\nImpotence in attempting to give some.","postedToGit":true,"htmlFragment":"<li class=\"pane\">\n  <div class=\"time-stamp entry-meta\">\n    <a href=\"seance-iKTZkVTr.html\">\n      <time datetime=\"2018-08-25T23:35:16.357Z\">2018-8-25 19:35:16</time>\n    </a>\n  </div><div class=\"text-caption\">⊹  ⊹  · ✵ ⊹  ✧✷   ✫  .\nImpotence in attempting to give some.</div>\n</li>","postedSingleVideoPage":true},{"id":"seance-QfFRYbqy","date":"2018-08-26T05:35:27.977Z","caption":"܃ം݄˳݅ ܀݅ ം◌:݃܈◌݄˳…݆˚܄܂°܇\nSaunter through his influence on others is often less severe.","postedToGit":true,"htmlFragment":"<li class=\"pane\">\n  <div class=\"time-stamp entry-meta\">\n    <a href=\"seance-QfFRYbqy.html\">\n      <time datetime=\"2018-08-26T05:35:27.977Z\">2018-8-26 01:35:27</time>\n    </a>\n  </div><div class=\"text-caption\">܃ം݄˳݅ ܀݅ ം◌:݃܈◌݄˳…݆˚܄܂°܇\nSaunter through his influence on others is often less severe.</div>\n</li>","postedSingleVideoPage":true},{"id":"seance-iCNUBEba","date":"2018-08-26T14:35:13.728Z","caption":"⥥⟱ ⟱⥥\nFertilizer in increasing his fortune.","postedToGit":true,"htmlFragment":"<li class=\"pane\">\n  <div class=\"time-stamp entry-meta\">\n    <a href=\"seance-iCNUBEba.html\">\n      <time datetime=\"2018-08-26T14:35:13.728Z\">2018-8-26 10:35:13</time>\n    </a>\n  </div><div class=\"text-caption\">⥥⟱ ⟱⥥\nFertilizer in increasing his fortune.</div>\n</li>","postedSingleVideoPage":true},{"id":"seance-kaeNJxMs","date":"2018-08-26T23:35:22.960Z","caption":"¨܀܂...\nTeleconference on the part to be played is a matter.","postedToGit":true,"htmlFragment":"<li class=\"pane\">\n  <div class=\"time-stamp entry-meta\">\n    <a href=\"seance-kaeNJxMs.html\">\n      <time datetime=\"2018-08-26T23:35:22.960Z\">2018-8-26 19:35:22</time>\n    </a>\n  </div><div class=\"text-caption\">¨܀܂...\nTeleconference on the part to be played is a matter.</div>\n</li>","postedSingleVideoPage":true},{"id":"seance-ITsiIDWd","date":"2018-08-27T05:35:28.091Z","caption":"܅˚܃\nCodger who 's to go in with her for the last.","postedToGit":true,"htmlFragment":"<li class=\"pane\">\n  <div class=\"time-stamp entry-meta\">\n    <a href=\"seance-ITsiIDWd.html\">\n      <time datetime=\"2018-08-27T05:35:28.091Z\">2018-8-27 01:35:28</time>\n    </a>\n  </div><div class=\"text-caption\">܅˚܃\nCodger who 's to go in with her for the last.</div>\n</li>","postedSingleVideoPage":true},{"id":"seance-CyCMySSn","date":"2018-08-27T14:35:10.579Z","caption":"⥥⟱ ⟱⥥\nSealskin coat had the fine.","postedToGit":true,"htmlFragment":"<li class=\"pane\">\n  <div class=\"time-stamp entry-meta\">\n    <a href=\"seance-CyCMySSn.html\">\n      <time datetime=\"2018-08-27T14:35:10.579Z\">2018-8-27 10:35:10</time>\n    </a>\n  </div><div class=\"text-caption\">⥥⟱ ⟱⥥\nSealskin coat had the fine.</div>\n</li>","postedSingleVideoPage":true},{"id":"seance-EqneaTAZ","date":"2018-08-27T23:35:02.865Z","caption":"݂܂݁•.˳˳ം܁¨݂݀܃ﾟ܄݃˚़:ﾟ܈܀\n܆¨°˳•܂ﾟ\n","postedToGit":true,"htmlFragment":"<li class=\"pane\">\n  <div class=\"time-stamp entry-meta\">\n    <a href=\"seance-EqneaTAZ.html\">\n      <time datetime=\"2018-08-27T23:35:02.865Z\">2018-8-27 19:35:02</time>\n    </a>\n  </div><div class=\"text-caption\">݂܂݁•.˳˳ം܁¨݂݀܃ﾟ܄݃˚़:ﾟ܈܀\n܆¨°˳•܂ﾟ\n</div>\n</li>","postedSingleVideoPage":true},{"id":"seance-IVMsRsJx","date":"2018-08-28T05:35:25.854Z","caption":"⊹  ⊹  · ✵ ⊹  ✧✷   ✫  .\nLurches toward a common purpose or set of performance goals and measures for his job.","postedToGit":true,"htmlFragment":"<li class=\"pane\">\n  <div class=\"time-stamp entry-meta\">\n    <a href=\"seance-IVMsRsJx.html\">\n      <time datetime=\"2018-08-28T05:35:25.854Z\">2018-8-28 01:35:25</time>\n    </a>\n  </div><div class=\"text-caption\">⊹  ⊹  · ✵ ⊹  ✧✷   ✫  .\nLurches toward a common purpose or set of performance goals and measures for his job.</div>\n</li>","postedSingleVideoPage":true},{"id":"seance-vSGgWiDs","date":"2018-08-28T14:35:12.804Z","caption":"⊹  ⊹  · ✵ ⊹  ✧✷   ✫  .\nCanyon and falls of the road.","postedToGit":true,"htmlFragment":"<li class=\"pane\">\n  <div class=\"time-stamp entry-meta\">\n    <a href=\"seance-vSGgWiDs.html\">\n      <time datetime=\"2018-08-28T14:35:12.804Z\">2018-8-28 10:35:12</time>\n    </a>\n  </div><div class=\"text-caption\">⊹  ⊹  · ✵ ⊹  ✧✷   ✫  .\nCanyon and falls of the road.</div>\n</li>","postedSingleVideoPage":true},{"id":"seance-TKgeIHXk","date":"2018-08-28T23:35:16.225Z","caption":"⊹  ⊹  · ✵ ⊹  ✧✷   ✫  .\nGents ⟰ of ⟰ that ⟰ sort ⟰ is ⟰ at ⟰ hand.","postedToGit":true,"htmlFragment":"<li class=\"pane\">\n  <div class=\"time-stamp entry-meta\">\n    <a href=\"seance-TKgeIHXk.html\">\n      <time datetime=\"2018-08-28T23:35:16.225Z\">2018-8-28 19:35:16</time>\n    </a>\n  </div><div class=\"text-caption\">⊹  ⊹  · ✵ ⊹  ✧✷   ✫  .\nGents ⟰ of ⟰ that ⟰ sort ⟰ is ⟰ at ⟰ hand.</div>\n</li>","postedSingleVideoPage":true},{"id":"seance-mVCVTgiv","date":"2018-08-29T05:35:16.343Z","caption":"⊹  ⊹  · ✵ ⊹  ✧✷   ✫  .\nSealer ⥥ for ⥥ a ⥥ period ⥥ varying ⥥ between ⥥ one.","postedToGit":true,"htmlFragment":"<li class=\"pane\">\n  <div class=\"time-stamp entry-meta\">\n    <a href=\"seance-mVCVTgiv.html\">\n      <time datetime=\"2018-08-29T05:35:16.343Z\">2018-8-29 01:35:16</time>\n    </a>\n  </div><div class=\"text-caption\">⊹  ⊹  · ✵ ⊹  ✧✷   ✫  .\nSealer ⥥ for ⥥ a ⥥ period ⥥ varying ⥥ between ⥥ one.</div>\n</li>","postedSingleVideoPage":true},{"id":"seance-zkngohNx","date":"2018-08-29T14:35:22.131Z","caption":"⥥⟱ ⟱⥥\nPull-ups for their support by the sweat of thy.","postedToGit":true,"htmlFragment":"<li class=\"pane\">\n  <div class=\"time-stamp entry-meta\">\n    <a href=\"seance-zkngohNx.html\">\n      <time datetime=\"2018-08-29T14:35:22.131Z\">2018-8-29 10:35:22</time>\n    </a>\n  </div><div class=\"text-caption\">⥥⟱ ⟱⥥\nPull-ups for their support by the sweat of thy.</div>\n</li>","postedSingleVideoPage":true},{"id":"seance-sVXeyJlH","date":"2018-08-29T23:35:38.306Z","caption":"…ം܆݃·܅°݆܄\nStorey to give them their true name and rank on a per pupil basis for comparison.","postedToGit":true,"htmlFragment":"<li class=\"pane\">\n  <div class=\"time-stamp entry-meta\">\n    <a href=\"seance-sVXeyJlH.html\">\n      <time datetime=\"2018-08-29T23:35:38.306Z\">2018-8-29 19:35:38</time>\n    </a>\n  </div><div class=\"text-caption\">…ം܆݃·܅°݆܄\nStorey to give them their true name and rank on a per pupil basis for comparison.</div>\n</li>","postedSingleVideoPage":true},{"id":"seance-xRQfJdYm","date":"2018-08-30T05:35:22.730Z","caption":"˳˳܇……܇݂\nConcierge is the result of our own observation.","postedToGit":true,"htmlFragment":"<li class=\"pane\">\n  <div class=\"time-stamp entry-meta\">\n    <a href=\"seance-xRQfJdYm.html\">\n      <time datetime=\"2018-08-30T05:35:22.730Z\">2018-8-30 01:35:22</time>\n    </a>\n  </div><div class=\"text-caption\">˳˳܇……܇݂\nConcierge is the result of our own observation.</div>\n</li>","postedSingleVideoPage":true},{"id":"seance-TTxkbZtd","date":"2018-08-30T14:35:27.113Z","caption":"⥥⟱ ⟱⥥\nPaella or a man of the people to be more.","postedToGit":true,"htmlFragment":"<li class=\"pane\">\n  <div class=\"time-stamp entry-meta\">\n    <a href=\"seance-TTxkbZtd.html\">\n      <time datetime=\"2018-08-30T14:35:27.113Z\">2018-8-30 10:35:27</time>\n    </a>\n  </div><div class=\"text-caption\">⥥⟱ ⟱⥥\nPaella or a man of the people to be more.</div>\n</li>","postedSingleVideoPage":true},{"id":"seance-HomtguOP","date":"2018-08-30T23:35:06.109Z","caption":"⊹  ⊹  · ✵ ⊹  ✧✷   ✫  .\nRomanticism is something.","postedToGit":true,"htmlFragment":"<li class=\"pane\">\n  <div class=\"time-stamp entry-meta\">\n    <a href=\"seance-HomtguOP.html\">\n      <time datetime=\"2018-08-30T23:35:06.109Z\">2018-8-30 19:35:06</time>\n    </a>\n  </div><div class=\"text-caption\">⊹  ⊹  · ✵ ⊹  ✧✷   ✫  .\nRomanticism is something.</div>\n</li>","postedSingleVideoPage":true},{"id":"seance-guezsbVv","date":"2018-08-31T05:35:10.604Z","caption":"⥥⟱ ⟱⥥\nSubpage is very material.","postedToGit":true,"htmlFragment":"<li class=\"pane\">\n  <div class=\"time-stamp entry-meta\">\n    <a href=\"seance-guezsbVv.html\">\n      <time datetime=\"2018-08-31T05:35:10.604Z\">2018-8-31 01:35:10</time>\n    </a>\n  </div><div class=\"text-caption\">⥥⟱ ⟱⥥\nSubpage is very material.</div>\n</li>","postedSingleVideoPage":true}]